mmWrt/Plots.py
mmWrt/PointCloud.py
mmWrt/RadarSignalProcessing.py
mmWrt/Raytracing.py
mmWrt/Scene.py
mmWrt/__init__.py
mmWrt/fmcw.py
mmWrt-0.0.8.dist-info/LICENSE
mmWrt-0.0.8.dist-info/METADATA
mmWrt-0.0.8.dist-info/WHEEL
mmWrt-0.0.8.dist-info/top_level.txt
mmWrt-0.0.8.dist-info/RECORD
